{"http://rdfs.org/ns/void#inDataset": ["https://situx.github.io/cuneiformontology/cunei_dataset"], "http://www.purl.org/graphemon#hasGraphemeReading": ["https://situx.github.io/cuneiformontology/signlist/character_za_musz3@g_ab@g_reading_za_musz3@g_ab@g"], "http://www.purl.org/graphemon#unicodeRepresentation": ["\ud808\udf5d\ud808\ude3d\ud808\udc15"], "http://www.w3.org/1999/02/22-rdf-syntax-ns#type": ["http://www.purl.org/graphemon#GraphemeComposition"], "http://www.w3.org/2000/01/rdf-schema#label": ["Character Composition: |za.musz3@g.ab@g|"]}