{"http://rdfs.org/ns/void#inDataset": ["https://situx.github.io/cuneiformontology/cunei_dataset"], "http://www.purl.org/graphemon#hasGraphemeReading": ["https://situx.github.io/cuneiformontology/signlist/character_dim9_reading_dim9", "https://situx.github.io/cuneiformontology/signlist/character_dim9_reading_lugal_gan"], "http://www.purl.org/graphemon#hasPart": ["https://situx.github.io/cuneiformontology/signlist/character_dim9_lugal", "https://situx.github.io/cuneiformontology/signlist/character_gan"], "http://www.purl.org/graphemon#meszl": ["267"], "http://www.purl.org/graphemon#signName": ["DIM9 (LUGAL.GAN)"], "http://www.purl.org/graphemon#slha": ["150v2"], "http://www.purl.org/graphemon#unicodeCodepoint": ["U+12217 & U+120F6"], "http://www.purl.org/graphemon#unicodeRepresentation": ["\ud808\ude17\ud808\udcf6"], "http://www.w3.org/1999/02/22-rdf-syntax-ns#type": ["http://www.purl.org/graphemon#GraphemeComposition"], "http://www.w3.org/2000/01/rdf-schema#label": ["Character Composition: DIM9 (LUGAL.GAN)"]}