{"http://rdfs.org/ns/void#inDataset": ["https://situx.github.io/cuneiformontology/cunei_dataset"], "http://www.purl.org/graphemon#abzl": ["036"], "http://www.purl.org/graphemon#hasGraphemeReading": ["https://situx.github.io/cuneiformontology/signlist/character_sa4_reading_hu_na2", "https://situx.github.io/cuneiformontology/signlist/character_sa4_reading_sa4", "https://situx.github.io/cuneiformontology/signlist/character_sa4_reading_sa4_k", "https://situx.github.io/cuneiformontology/signlist/character_sa4_reading_sza22", "https://situx.github.io/cuneiformontology/signlist/character_sa4_reading_sze21"], "http://www.purl.org/graphemon#hasPart": ["https://situx.github.io/cuneiformontology/signlist/character_na2", "https://situx.github.io/cuneiformontology/signlist/character_sa4_hu"], "http://www.purl.org/graphemon#labat": ["82"], "http://www.purl.org/graphemon#meszl": ["138"], "http://www.purl.org/graphemon#obo": ["136"], "http://www.purl.org/graphemon#signName": ["SA4 (\u1e2aU.N\u00c1)"], "http://www.purl.org/graphemon#slha": ["082"], "http://www.purl.org/graphemon#unicodeCodepoint": ["U+12137 & U+1223F"], "http://www.purl.org/graphemon#unicodeRepresentation": ["\ud808\udd37\ud808\ude3f"], "http://www.w3.org/1999/02/22-rdf-syntax-ns#type": ["http://www.purl.org/graphemon#GraphemeComposition"], "http://www.w3.org/2000/01/rdf-schema#label": ["Character Composition: SA4 (\u1e2aU.N\u00c1)"]}