{"http://lemon-model.net/lemon#sense": ["https://situx.github.io/cuneiformontology/signlist/character_s\u00ecla_sense_a_measure", "https://situx.github.io/cuneiformontology/signlist/character_s\u00ecla_sense_measuring_pot"], "http://rdfs.org/ns/void#inDataset": ["https://situx.github.io/cuneiformontology/cunei_dataset"], "http://www.purl.org/graphemon#abzl": ["269"], "http://www.purl.org/graphemon#hasGraphemeReading": ["https://situx.github.io/cuneiformontology/signlist/character_s\u00ecla_reading_aq_k", "https://situx.github.io/cuneiformontology/signlist/character_s\u00ecla_reading_ga5", "https://situx.github.io/cuneiformontology/signlist/character_s\u00ecla_reading_ka4", "https://situx.github.io/cuneiformontology/signlist/character_s\u00ecla_reading_qa", "https://situx.github.io/cuneiformontology/signlist/character_s\u00ecla_reading_q\u00fb", "https://situx.github.io/cuneiformontology/signlist/character_s\u00ecla_reading_sal4", "https://situx.github.io/cuneiformontology/signlist/character_s\u00ecla_reading_sala4", "https://situx.github.io/cuneiformontology/signlist/character_s\u00ecla_reading_sil3", "https://situx.github.io/cuneiformontology/signlist/character_s\u00ecla_reading_sila3", "https://situx.github.io/cuneiformontology/signlist/character_s\u00ecla_reading_sila3_qa", "https://situx.github.io/cuneiformontology/signlist/character_s\u00ecla_reading_sila3_sila3", "https://situx.github.io/cuneiformontology/signlist/character_s\u00ecla_reading_sila3\u00a0_q\u016bm", "https://situx.github.io/cuneiformontology/signlist/character_s\u00ecla_reading_szal2"], "http://www.purl.org/graphemon#hasPart": ["https://situx.github.io/cuneiformontology/signlist/character_si3la"], "http://www.purl.org/graphemon#hethzl": ["21"], "http://www.purl.org/graphemon#labat": ["62"], "http://www.purl.org/graphemon#meszl": ["99"], "http://www.purl.org/graphemon#obo": ["269"], "http://www.purl.org/graphemon#signName": ["S\u00ccLA"], "http://www.purl.org/graphemon#slha": ["062"], "http://www.purl.org/graphemon#unicodeCodepoint": ["U+122E1"], "http://www.purl.org/graphemon#unicodeRepresentation": ["\ud808\udee1"], "http://www.w3.org/1999/02/22-rdf-syntax-ns#type": ["http://www.purl.org/graphemon#Grapheme"], "http://www.w3.org/2000/01/rdf-schema#label": ["Character: S\u00ccLA"], "http://www.w3.org/2002/07/owl#sameAs": ["http://www.wikidata.org/entity/Q87556449"]}