{"http://rdfs.org/ns/void#inDataset": ["https://situx.github.io/cuneiformontology/cunei_dataset"], "http://www.purl.org/graphemon#hasPart": ["https://situx.github.io/cuneiformontology/signlist/character_ge23", "https://situx.github.io/cuneiformontology/signlist/character_lagab"], "http://www.purl.org/graphemon#meszl": ["778"], "http://www.purl.org/graphemon#signName": ["LAGAB\u00d7GE23"], "http://www.purl.org/graphemon#slha": ["504"], "http://www.purl.org/graphemon#unicodeCodepoint": ["U+121BF"], "http://www.purl.org/graphemon#unicodeRepresentation": ["\ud808\uddbf"], "http://www.w3.org/1999/02/22-rdf-syntax-ns#type": ["http://www.purl.org/graphemon#Grapheme"], "http://www.w3.org/2000/01/rdf-schema#label": ["Character: LAGAB\u00d7GE23"], "http://www.w3.org/2002/07/owl#sameAs": ["http://www.wikidata.org/entity/Q87555896"]}